README.rst
arf.py
arf-2.7.1.dist-info/METADATA
arf-2.7.1.dist-info/WHEEL
arf-2.7.1.dist-info/licenses/COPYING
arf-2.7.1.dist-info/RECORD
