Metadata-Version: 2.4
Name: arf
Version: 2.7.1
Summary: Advanced Recording Format for acoustic, behavioral, and physiological data
Project-URL: Homepage, https://github.com/melizalab/arf
Author-email: Dan Meliza <dan@meliza.org>
Maintainer-email: Dan Meliza <dan@meliza.org>
License: BSD 3-Clause License
License-File: COPYING
Keywords: data format,neuroscience
Classifier: Development Status :: 5 - Production/Stable
Classifier: Intended Audience :: Science/Research
Classifier: License :: OSI Approved :: BSD License
Classifier: Natural Language :: English
Classifier: Operating System :: MacOS :: MacOS X
Classifier: Operating System :: Microsoft :: Windows
Classifier: Operating System :: POSIX :: Linux
Classifier: Operating System :: Unix
Classifier: Programming Language :: C++
Classifier: Programming Language :: Python
Classifier: Programming Language :: Python :: 3.7
Classifier: Programming Language :: Python :: 3.8
Classifier: Programming Language :: Python :: 3.9
Classifier: Programming Language :: Python :: 3.10
Classifier: Programming Language :: Python :: 3.11
Classifier: Programming Language :: Python :: 3.12
Classifier: Topic :: Scientific/Engineering
Requires-Python: >=3.7
Requires-Dist: h5py>=3.11.0; python_version == '3.8'
Requires-Dist: h5py>=3.12.1; python_version >= '3.9'
Requires-Dist: h5py>=3.8.0; python_version == '3.7'
Requires-Dist: numpy>=1.21.6; python_version == '3.7'
Requires-Dist: numpy>=1.23.2; python_version == '3.10'
Requires-Dist: numpy>=1.23.2; python_version == '3.8'
Requires-Dist: numpy>=1.23.2; python_version == '3.9'
Requires-Dist: numpy>=1.24.0; python_version == '3.11'
Requires-Dist: numpy>=1.26.0; python_version == '3.12'
Requires-Dist: numpy>=2.2.1; python_version >= '3.13'
Requires-Dist: packaging>=24.0
